{
  "page": 513,
  "font": "QCF4_Warsh_43",
  "surahs": [
    {
      "id": 48,
      "name": "Al-Fath",
      "name_arabic": "Ш§Щ„ЩҒШӘШӯ",
      "verse_start": 16,
      "verse_end": 23
    }
  ],
  "lines": [
    {
      "line": 1,
      "words": [
        {
          "code": 61696,
          "char": "п„Җ",
          "font": "QCF4_Warsh_43",
          "text": "ЩӮЩҸЩ„",
          "type": "word",
          "verse_key": "48:16",
          "position": 1
        },
        {
          "code": 61697,
          "char": "п„Ғ",
          "font": "QCF4_Warsh_43",
          "text": "Щ„Щ‘ЩҗЩ„Щ’Щ…ЩҸШ®ЩҺЩ„Щ‘ЩҺЩҒЩҗЩҠЩҶЩҺ",
          "type": "word",
          "verse_key": "48:16",
          "position": 2
        },
        {
          "code": 61698,
          "char": "п„Ӯ",
          "font": "QCF4_Warsh_43",
          "text": "Щ…ЩҗЩҶЩҺ",
          "type": "word",
          "verse_key": "48:16",
          "position": 3
        },
        {
          "code": 61699,
          "char": "п„ғ",
          "font": "QCF4_Warsh_43",
          "text": "Ш§ЩҺЫ¬Щ„ЩҺШ§Ш№Щ’ШұЩҺШ§ШЁЩҗ",
          "type": "word_with_mark",
          "verse_key": "48:16",
          "position": 4
        },
        {
          "code": 61700,
          "char": "п„„",
          "font": "QCF4_Warsh_43",
          "text": "ШіЩҺШӘЩҸШҜЩ’Ш№ЩҺЩҲЩ’ЩҶЩҺ",
          "type": "word",
          "verse_key": "48:16",
          "position": 5
        },
        {
          "code": 61701,
          "char": "п„…",
          "font": "QCF4_Warsh_43",
          "text": "ШҘЩҗЩ„ЩҺЩүЩ°",
          "type": "word",
          "verse_key": "48:16",
          "position": 6
        },
        {
          "code": 61702,
          "char": "п„Ҷ",
          "font": "QCF4_Warsh_43",
          "text": "ЩӮЩҺЩҲЩ’Щ…ЩҚ",
          "type": "word",
          "verse_key": "48:16",
          "position": 7
        },
        {
          "code": 61703,
          "char": "п„Ү",
          "font": "QCF4_Warsh_43",
          "text": "Ш§ЫҹЩҲЩ’Щ„ЩҗЫ’",
          "type": "word_with_mark",
          "verse_key": "48:16",
          "position": 8
        },
        {
          "code": 61704,
          "char": "п„Ҳ",
          "font": "QCF4_Warsh_43",
          "text": "ШЁЩҺШЈЩ’ШіЩ–",
          "type": "word",
          "verse_key": "48:16",
          "position": 9
        },
        {
          "code": 61705,
          "char": "п„ү",
          "font": "QCF4_Warsh_43",
          "text": "ШҙЩҺШҜЩҗЩҠШҜЩ–",
          "type": "word",
          "verse_key": "48:16",
          "position": 10
        }
      ]
    },
    {
      "line": 2,
      "words": [
        {
          "code": 61706,
          "char": "п„Ҡ",
          "font": "QCF4_Warsh_43",
          "text": "ШӘЩҸЩӮЩҺЩ°ШӘЩҗЩ„ЩҸЩҲЩҶЩҺЩҮЩҸЩ…ЩҸЫҘЩ“",
          "type": "word_with_mark",
          "verse_key": "48:16",
          "position": 11
        },
        {
          "code": 61707,
          "char": "п„Ӣ",
          "font": "QCF4_Warsh_43",
          "text": "ШЈЩҺЩҲЩ’",
          "type": "word",
          "verse_key": "48:16",
          "position": 12
        },
        {
          "code": 61708,
          "char": "п„Ң",
          "font": "QCF4_Warsh_43",
          "text": "ЩҠЩҸШіЩ’Щ„ЩҗЩ…ЩҸЩҲЩҶЩҺЫ–",
          "type": "word_with_mark",
          "verse_key": "48:16",
          "position": 13
        },
        {
          "code": 61710,
          "char": "п„Һ",
          "font": "QCF4_Warsh_43",
          "text": "ЩҒЩҺШҘЩҗЩҶ",
          "type": "word",
          "verse_key": "48:16",
          "position": 14
        },
        {
          "code": 61711,
          "char": "п„Ҹ",
          "font": "QCF4_Warsh_43",
          "text": "ШӘЩҸШ·ЩҗЩҠШ№ЩҸЩҲШ§Щ’",
          "type": "word",
          "verse_key": "48:16",
          "position": 15
        },
        {
          "code": 61712,
          "char": "п„җ",
          "font": "QCF4_Warsh_43",
          "text": "ЩҠЩҸЩҲШӘЩҗЩғЩҸЩ…ЩҸ",
          "type": "word",
          "verse_key": "48:16",
          "position": 16
        },
        {
          "code": 61713,
          "char": "п„‘",
          "font": "QCF4_Warsh_43",
          "text": "Ш§ЩҸЫ¬Щ„Щ„Щ‘ЩҺЩҮЩҸ",
          "type": "word_with_mark",
          "verse_key": "48:16",
          "position": 17
        },
        {
          "code": 61714,
          "char": "п„’",
          "font": "QCF4_Warsh_43",
          "text": "ШЈЩҺШ¬Щ’ШұШ§ЩӢ",
          "type": "word",
          "verse_key": "48:16",
          "position": 18
        },
        {
          "code": 61715,
          "char": "п„“",
          "font": "QCF4_Warsh_43",
          "text": "ШӯЩҺШіЩҺЩҶШ§Щ—Ы–",
          "type": "word_with_mark",
          "verse_key": "48:16",
          "position": 19
        }
      ]
    },
    {
      "line": 3,
      "words": [
        {
          "code": 61717,
          "char": "п„•",
          "font": "QCF4_Warsh_43",
          "text": "ЩҲЩҺШҘЩҗЩҶ",
          "type": "word",
          "verse_key": "48:16",
          "position": 20
        },
        {
          "code": 61718,
          "char": "п„–",
          "font": "QCF4_Warsh_43",
          "text": "ШӘЩҺШӘЩҺЩҲЩҺЩ„Щ‘ЩҺЩҲЩ’Ш§Щ’",
          "type": "word",
          "verse_key": "48:16",
          "position": 21
        },
        {
          "code": 61719,
          "char": "п„—",
          "font": "QCF4_Warsh_43",
          "text": "ЩғЩҺЩ…ЩҺШ§",
          "type": "word",
          "verse_key": "48:16",
          "position": 22
        },
        {
          "code": 61720,
          "char": "п„ҳ",
          "font": "QCF4_Warsh_43",
          "text": "ШӘЩҺЩҲЩҺЩ„Щ‘ЩҺЩҠЩ’ШӘЩҸЩ…",
          "type": "word",
          "verse_key": "48:16",
          "position": 23
        },
        {
          "code": 61721,
          "char": "п„ҷ",
          "font": "QCF4_Warsh_43",
          "text": "Щ…Щ‘ЩҗЩҶ",
          "type": "word",
          "verse_key": "48:16",
          "position": 24
        },
        {
          "code": 61722,
          "char": "п„ҡ",
          "font": "QCF4_Warsh_43",
          "text": "ЩӮЩҺШЁЩ’Щ„ЩҸ",
          "type": "word",
          "verse_key": "48:16",
          "position": 25
        },
        {
          "code": 61723,
          "char": "п„ӣ",
          "font": "QCF4_Warsh_43",
          "text": "ЩҠЩҸШ№ЩҺШ°Щ‘ЩҗШЁЩ’ЩғЩҸЩ…Щ’",
          "type": "word",
          "verse_key": "48:16",
          "position": 26
        },
        {
          "code": 61724,
          "char": "п„ң",
          "font": "QCF4_Warsh_43",
          "text": "Ш№ЩҺШ°ЩҺШ§ШЁШ§ЩӢ",
          "type": "word",
          "verse_key": "48:16",
          "position": 27
        },
        {
          "code": 61725,
          "char": "п„қ",
          "font": "QCF4_Warsh_43",
          "text": "Ш§ЩҺЩ„ЩҗЩҠЩ…Ш§Щ—Ы–",
          "type": "word_with_mark",
          "verse_key": "48:16",
          "position": 28
        },
        {
          "code": 61727,
          "char": "п„ҹ",
          "font": "QCF4_Warsh_43",
          "text": "16",
          "type": "aya_end",
          "verse_key": "48:16",
          "aya_num": 16
        },
        {
          "code": 61728,
          "char": "п„ ",
          "font": "QCF4_Warsh_43",
          "text": "Щ„Щ‘ЩҺЩҠЩ’ШіЩҺ",
          "type": "word",
          "verse_key": "48:17",
          "position": 1
        }
      ]
    },
    {
      "line": 4,
      "words": [
        {
          "code": 61729,
          "char": "п„Ў",
          "font": "QCF4_Warsh_43",
          "text": "Ш№ЩҺЩ„ЩҺЩү",
          "type": "word",
          "verse_key": "48:17",
          "position": 2
        },
        {
          "code": 61730,
          "char": "п„ў",
          "font": "QCF4_Warsh_43",
          "text": "Ш§ЩҺЫ¬Щ„ЩҺШ§Ш№Щ’Щ…ЫӘЩүЩ°",
          "type": "word_with_mark",
          "verse_key": "48:17",
          "position": 3
        },
        {
          "code": 61731,
          "char": "п„Ј",
          "font": "QCF4_Warsh_43",
          "text": "ШӯЩҺШұЩҺШ¬Щһ",
          "type": "word",
          "verse_key": "48:17",
          "position": 4
        },
        {
          "code": 61732,
          "char": "п„Ө",
          "font": "QCF4_Warsh_43",
          "text": "ЩҲЩҺЩ„ЩҺШ§",
          "type": "word",
          "verse_key": "48:17",
          "position": 5
        },
        {
          "code": 61733,
          "char": "п„Ҙ",
          "font": "QCF4_Warsh_43",
          "text": "Ш№ЩҺЩ„ЩҺЩү",
          "type": "word",
          "verse_key": "48:17",
          "position": 6
        },
        {
          "code": 61734,
          "char": "п„Ұ",
          "font": "QCF4_Warsh_43",
          "text": "Ш§ЩҺЫ¬Щ„ЩҺШ§Ш№Щ’ШұЩҺШ¬Щҗ",
          "type": "word_with_mark",
          "verse_key": "48:17",
          "position": 7
        },
        {
          "code": 61735,
          "char": "п„§",
          "font": "QCF4_Warsh_43",
          "text": "ШӯЩҺШұЩҺШ¬Щһ",
          "type": "word",
          "verse_key": "48:17",
          "position": 8
        },
        {
          "code": 61736,
          "char": "п„Ё",
          "font": "QCF4_Warsh_43",
          "text": "ЩҲЩҺЩ„ЩҺШ§",
          "type": "word",
          "verse_key": "48:17",
          "position": 9
        },
        {
          "code": 61737,
          "char": "п„©",
          "font": "QCF4_Warsh_43",
          "text": "Ш№ЩҺЩ„ЩҺЩү",
          "type": "word",
          "verse_key": "48:17",
          "position": 10
        },
        {
          "code": 61738,
          "char": "п„Ә",
          "font": "QCF4_Warsh_43",
          "text": "Ш§ЩҺЫ¬Щ„Щ’Щ…ЩҺШұЩҗЩҠШ¶Щҗ",
          "type": "word_with_mark",
          "verse_key": "48:17",
          "position": 11
        },
        {
          "code": 61739,
          "char": "п„«",
          "font": "QCF4_Warsh_43",
          "text": "ШӯЩҺШұЩҺШ¬ЩһЫ–",
          "type": "word_with_mark",
          "verse_key": "48:17",
          "position": 12
        }
      ]
    },
    {
      "line": 5,
      "words": [
        {
          "code": 61741,
          "char": "п„ӯ",
          "font": "QCF4_Warsh_43",
          "text": "ЩҲЩҺЩ…ЩҺЩҶЩ’",
          "type": "word",
          "verse_key": "48:17",
          "position": 13
        },
        {
          "code": 61742,
          "char": "п„®",
          "font": "QCF4_Warsh_43",
          "text": "ЩҠЩ‘ЩҸШ·ЩҗШ№Щҗ",
          "type": "word",
          "verse_key": "48:17",
          "position": 14
        },
        {
          "code": 61743,
          "char": "п„Ҝ",
          "font": "QCF4_Warsh_43",
          "text": "Ш§ЩҗЫ¬Щ„Щ„Щ‘ЩҺЩҮЩҺ",
          "type": "word_with_mark",
          "verse_key": "48:17",
          "position": 15
        },
        {
          "code": 61744,
          "char": "п„°",
          "font": "QCF4_Warsh_43",
          "text": "ЩҲЩҺШұЩҺШіЩҸЩҲЩ„ЩҺЩҮЩҸЫҘ",
          "type": "word_with_mark",
          "verse_key": "48:17",
          "position": 16
        },
        {
          "code": 61745,
          "char": "п„ұ",
          "font": "QCF4_Warsh_43",
          "text": "ЩҶЩҸШҜЩ’Ш®ЩҗЩ„Щ’ЩҮЩҸ",
          "type": "word",
          "verse_key": "48:17",
          "position": 17
        },
        {
          "code": 61746,
          "char": "п„І",
          "font": "QCF4_Warsh_43",
          "text": "Ш¬ЩҺЩҶЩ‘ЩҺЩ°ШӘЩ–",
          "type": "word",
          "verse_key": "48:17",
          "position": 18
        },
        {
          "code": 61747,
          "char": "п„і",
          "font": "QCF4_Warsh_43",
          "text": "ШӘЩҺШ¬Щ’ШұЩҗЫ’",
          "type": "word",
          "verse_key": "48:17",
          "position": 19
        },
        {
          "code": 61748,
          "char": "п„ҙ",
          "font": "QCF4_Warsh_43",
          "text": "Щ…ЩҗЩҶ",
          "type": "word",
          "verse_key": "48:17",
          "position": 20
        },
        {
          "code": 61749,
          "char": "п„ө",
          "font": "QCF4_Warsh_43",
          "text": "ШӘЩҺШӯЩ’ШӘЩҗЩҮЩҺШ§",
          "type": "word",
          "verse_key": "48:17",
          "position": 21
        }
      ]
    },
    {
      "line": 6,
      "words": [
        {
          "code": 61750,
          "char": "п„¶",
          "font": "QCF4_Warsh_43",
          "text": "Ш§ЩҺЫ¬Щ„ЩҺШ§ЩҶЩ’ЩҮЩҺЩ°ШұЩҸЫ–",
          "type": "word_with_mark",
          "verse_key": "48:17",
          "position": 22
        },
        {
          "code": 61752,
          "char": "п„ё",
          "font": "QCF4_Warsh_43",
          "text": "ЩҲЩҺЩ…ЩҺЩҶЩ’",
          "type": "word",
          "verse_key": "48:17",
          "position": 23
        },
        {
          "code": 61753,
          "char": "п„№",
          "font": "QCF4_Warsh_43",
          "text": "ЩҠЩ‘ЩҺШӘЩҺЩҲЩҺЩ„Щ‘ЩҺ",
          "type": "word",
          "verse_key": "48:17",
          "position": 24
        },
        {
          "code": 61754,
          "char": "п„ә",
          "font": "QCF4_Warsh_43",
          "text": "ЩҶЩҸШ№ЩҺШ°Щ‘ЩҗШЁЩ’ЩҮЩҸ",
          "type": "word",
          "verse_key": "48:17",
          "position": 25
        },
        {
          "code": 61755,
          "char": "п„»",
          "font": "QCF4_Warsh_43",
          "text": "Ш№ЩҺШ°ЩҺШ§ШЁШ§ЩӢ",
          "type": "word",
          "verse_key": "48:17",
          "position": 26
        },
        {
          "code": 61756,
          "char": "п„ј",
          "font": "QCF4_Warsh_43",
          "text": "Ш§ЩҺЩ„ЩҗЩҠЩ…Ш§Щ—Ы–",
          "type": "word_with_mark",
          "verse_key": "48:17",
          "position": 27
        },
        {
          "code": 61758,
          "char": "п„ҫ",
          "font": "QCF4_Warsh_43",
          "text": "17",
          "type": "aya_end",
          "verse_key": "48:17",
          "aya_num": 17
        },
        {
          "code": 61759,
          "char": "п„ҝ",
          "font": "QCF4_Warsh_43",
          "text": "Ыһ",
          "type": "special_standalone",
          "verse_key": "48:18",
          "position": 1
        },
        {
          "code": 61760,
          "char": "п…Җ",
          "font": "QCF4_Warsh_43",
          "text": "Щ„Щ‘ЩҺЩӮЩҺШҜЩ’",
          "type": "word",
          "verse_key": "48:18",
          "position": 2
        },
        {
          "code": 61761,
          "char": "п…Ғ",
          "font": "QCF4_Warsh_43",
          "text": "ШұЩҺШ¶ЩҗЩҠЩҺ",
          "type": "word",
          "verse_key": "48:18",
          "position": 3
        },
        {
          "code": 61762,
          "char": "п…Ӯ",
          "font": "QCF4_Warsh_43",
          "text": "Ш§ЩҺЫ¬Щ„Щ„Щ‘ЩҺЩҮЩҸ",
          "type": "word_with_mark",
          "verse_key": "48:18",
          "position": 4
        }
      ]
    },
    {
      "line": 7,
      "words": [
        {
          "code": 61763,
          "char": "п…ғ",
          "font": "QCF4_Warsh_43",
          "text": "Ш№ЩҺЩҶЩҗ",
          "type": "word",
          "verse_key": "48:18",
          "position": 5
        },
        {
          "code": 61764,
          "char": "п…„",
          "font": "QCF4_Warsh_43",
          "text": "Ш§ЩҗЫ¬Щ„Щ’Щ…ЩҸЩҲЩ…ЩҗЩҶЩҗЩҠЩҶЩҺ",
          "type": "word_with_mark",
          "verse_key": "48:18",
          "position": 6
        },
        {
          "code": 61765,
          "char": "п……",
          "font": "QCF4_Warsh_43",
          "text": "ШҘЩҗШ°Щ’",
          "type": "word",
          "verse_key": "48:18",
          "position": 7
        },
        {
          "code": 61766,
          "char": "п…Ҷ",
          "font": "QCF4_Warsh_43",
          "text": "ЩҠЩҸШЁЩҺШ§ЩҠЩҗШ№ЩҸЩҲЩҶЩҺЩғЩҺ",
          "type": "word",
          "verse_key": "48:18",
          "position": 8
        },
        {
          "code": 61767,
          "char": "п…Ү",
          "font": "QCF4_Warsh_43",
          "text": "ШӘЩҺШӯЩ’ШӘЩҺ",
          "type": "word",
          "verse_key": "48:18",
          "position": 9
        },
        {
          "code": 61768,
          "char": "п…Ҳ",
          "font": "QCF4_Warsh_43",
          "text": "Ш§ЩҺЫ¬Щ„ШҙЩ‘ЩҺШ¬ЩҺШұЩҺШ©Щҗ",
          "type": "word_with_mark",
          "verse_key": "48:18",
          "position": 10
        },
        {
          "code": 61769,
          "char": "п…ү",
          "font": "QCF4_Warsh_43",
          "text": "ЩҒЩҺШ№ЩҺЩ„ЩҗЩ…ЩҺ",
          "type": "word",
          "verse_key": "48:18",
          "position": 11
        },
        {
          "code": 61770,
          "char": "п…Ҡ",
          "font": "QCF4_Warsh_43",
          "text": "Щ…ЩҺШ§",
          "type": "word",
          "verse_key": "48:18",
          "position": 12
        },
        {
          "code": 61771,
          "char": "п…Ӣ",
          "font": "QCF4_Warsh_43",
          "text": "ЩҒЩҗЫ’",
          "type": "word",
          "verse_key": "48:18",
          "position": 13
        }
      ]
    },
    {
      "line": 8,
      "words": [
        {
          "code": 61772,
          "char": "п…Ң",
          "font": "QCF4_Warsh_43",
          "text": "ЩӮЩҸЩ„ЩҸЩҲШЁЩҗЩҮЩҗЩ…Щ’",
          "type": "word",
          "verse_key": "48:18",
          "position": 14
        },
        {
          "code": 61773,
          "char": "п…Қ",
          "font": "QCF4_Warsh_43",
          "text": "ЩҒЩҺШЈЩҺЩҶШІЩҺЩ„ЩҺ",
          "type": "word",
          "verse_key": "48:18",
          "position": 15
        },
        {
          "code": 61774,
          "char": "п…Һ",
          "font": "QCF4_Warsh_43",
          "text": "Ш§ЩҺЫ¬Щ„ШіЩ‘ЩҺЩғЩҗЩҠЩҶЩҺШ©ЩҺ",
          "type": "word_with_mark",
          "verse_key": "48:18",
          "position": 16
        },
        {
          "code": 61775,
          "char": "п…Ҹ",
          "font": "QCF4_Warsh_43",
          "text": "Ш№ЩҺЩ„ЩҺЩҠЩ’ЩҮЩҗЩ…Щ’",
          "type": "word",
          "verse_key": "48:18",
          "position": 17
        },
        {
          "code": 61776,
          "char": "п…җ",
          "font": "QCF4_Warsh_43",
          "text": "ЩҲЩҺШЈЩҺШ«ЩҺЩ°ШЁЩҺЩҮЩҸЩ…Щ’",
          "type": "word",
          "verse_key": "48:18",
          "position": 18
        },
        {
          "code": 61777,
          "char": "п…‘",
          "font": "QCF4_Warsh_43",
          "text": "ЩҒЩҺШӘЩ’ШӯШ§Щ—",
          "type": "word",
          "verse_key": "48:18",
          "position": 19
        },
        {
          "code": 61778,
          "char": "п…’",
          "font": "QCF4_Warsh_43",
          "text": "ЩӮЩҺШұЩҗЩҠШЁШ§Щ—",
          "type": "word",
          "verse_key": "48:18",
          "position": 20
        },
        {
          "code": 61779,
          "char": "п…“",
          "font": "QCF4_Warsh_43",
          "text": "18",
          "type": "aya_end",
          "verse_key": "48:18",
          "aya_num": 18
        },
        {
          "code": 61780,
          "char": "п…”",
          "font": "QCF4_Warsh_43",
          "text": "ЩҲЩҺЩ…ЩҺШәЩҺШ§ЩҶЩҗЩ…ЩҺ",
          "type": "word",
          "verse_key": "48:19",
          "position": 1
        }
      ]
    },
    {
      "line": 9,
      "words": [
        {
          "code": 61781,
          "char": "п…•",
          "font": "QCF4_Warsh_43",
          "text": "ЩғЩҺШ«ЩҗЩҠШұЩҺШ©Щ—",
          "type": "word",
          "verse_key": "48:19",
          "position": 2
        },
        {
          "code": 61782,
          "char": "п…–",
          "font": "QCF4_Warsh_43",
          "text": "ЩҠЩҺШ§Ш®ЩҸШ°ЩҸЩҲЩҶЩҺЩҮЩҺШ§Ы–",
          "type": "word_with_mark",
          "verse_key": "48:19",
          "position": 3
        },
        {
          "code": 61784,
          "char": "п…ҳ",
          "font": "QCF4_Warsh_43",
          "text": "ЩҲЩҺЩғЩҺШ§ЩҶЩҺ",
          "type": "word",
          "verse_key": "48:19",
          "position": 4
        },
        {
          "code": 61785,
          "char": "п…ҷ",
          "font": "QCF4_Warsh_43",
          "text": "Ш§ЩҺЫ¬Щ„Щ„Щ‘ЩҺЩҮЩҸ",
          "type": "word_with_mark",
          "verse_key": "48:19",
          "position": 5
        },
        {
          "code": 61786,
          "char": "п…ҡ",
          "font": "QCF4_Warsh_43",
          "text": "Ш№ЩҺШІЩҗЩҠШІШ§ЩӢ",
          "type": "word",
          "verse_key": "48:19",
          "position": 6
        },
        {
          "code": 61787,
          "char": "п…ӣ",
          "font": "QCF4_Warsh_43",
          "text": "ШӯЩҺЩғЩҗЩҠЩ…Ш§Щ—Ы–",
          "type": "word_with_mark",
          "verse_key": "48:19",
          "position": 7
        },
        {
          "code": 61789,
          "char": "п…қ",
          "font": "QCF4_Warsh_43",
          "text": "19",
          "type": "aya_end",
          "verse_key": "48:19",
          "aya_num": 19
        },
        {
          "code": 61790,
          "char": "п…һ",
          "font": "QCF4_Warsh_43",
          "text": "ЩҲЩҺШ№ЩҺШҜЩҺЩғЩҸЩ…ЩҸ",
          "type": "word",
          "verse_key": "48:20",
          "position": 1
        },
        {
          "code": 61791,
          "char": "п…ҹ",
          "font": "QCF4_Warsh_43",
          "text": "Ш§ЩҸЫ¬Щ„Щ„Щ‘ЩҺЩҮЩҸ",
          "type": "word_with_mark",
          "verse_key": "48:20",
          "position": 2
        }
      ]
    },
    {
      "line": 10,
      "words": [
        {
          "code": 61792,
          "char": "п… ",
          "font": "QCF4_Warsh_43",
          "text": "Щ…ЩҺШәЩҺШ§ЩҶЩҗЩ…ЩҺ",
          "type": "word",
          "verse_key": "48:20",
          "position": 3
        },
        {
          "code": 61793,
          "char": "п…Ў",
          "font": "QCF4_Warsh_43",
          "text": "ЩғЩҺШ«ЩҗЩҠШұЩҺШ©Щ—",
          "type": "word",
          "verse_key": "48:20",
          "position": 4
        },
        {
          "code": 61794,
          "char": "п…ў",
          "font": "QCF4_Warsh_43",
          "text": "ШӘЩҺШ§Ш®ЩҸШ°ЩҸЩҲЩҶЩҺЩҮЩҺШ§",
          "type": "word",
          "verse_key": "48:20",
          "position": 5
        },
        {
          "code": 61795,
          "char": "п…Ј",
          "font": "QCF4_Warsh_43",
          "text": "ЩҒЩҺШ№ЩҺШ¬Щ‘ЩҺЩ„ЩҺ",
          "type": "word",
          "verse_key": "48:20",
          "position": 6
        },
        {
          "code": 61796,
          "char": "п…Ө",
          "font": "QCF4_Warsh_43",
          "text": "Щ„ЩҺЩғЩҸЩ…Щ’",
          "type": "word",
          "verse_key": "48:20",
          "position": 7
        },
        {
          "code": 61797,
          "char": "п…Ҙ",
          "font": "QCF4_Warsh_43",
          "text": "ЩҮЩҺЩ°Ш°ЩҗЩҮЩҗЫҰ",
          "type": "word_with_mark",
          "verse_key": "48:20",
          "position": 8
        },
        {
          "code": 61798,
          "char": "п…Ұ",
          "font": "QCF4_Warsh_43",
          "text": "ЩҲЩҺЩғЩҺЩҒЩ‘ЩҺ",
          "type": "word",
          "verse_key": "48:20",
          "position": 9
        },
        {
          "code": 61799,
          "char": "п…§",
          "font": "QCF4_Warsh_43",
          "text": "ШЈЩҺЩҠЩ’ШҜЩҗЩҠЩҺ",
          "type": "word",
          "verse_key": "48:20",
          "position": 10
        }
      ]
    },
    {
      "line": 11,
      "words": [
        {
          "code": 61800,
          "char": "п…Ё",
          "font": "QCF4_Warsh_43",
          "text": "Ш§ЩҺЫ¬Щ„ЩҶЩ‘ЩҺШ§ШіЩҗ",
          "type": "word_with_mark",
          "verse_key": "48:20",
          "position": 11
        },
        {
          "code": 61801,
          "char": "п…©",
          "font": "QCF4_Warsh_43",
          "text": "Ш№ЩҺЩҶЩғЩҸЩ…Щ’Ы–",
          "type": "word_with_mark",
          "verse_key": "48:20",
          "position": 12
        },
        {
          "code": 61803,
          "char": "п…«",
          "font": "QCF4_Warsh_43",
          "text": "ЩҲЩҺЩ„ЩҗШӘЩҺЩғЩҸЩҲЩҶЩҺ",
          "type": "word",
          "verse_key": "48:20",
          "position": 13
        },
        {
          "code": 61804,
          "char": "п…¬",
          "font": "QCF4_Warsh_43",
          "text": "ШЎЩҺШ§ЩҠЩҺШ©Щ—",
          "type": "word",
          "verse_key": "48:20",
          "position": 14
        },
        {
          "code": 61805,
          "char": "п…ӯ",
          "font": "QCF4_Warsh_43",
          "text": "Щ„Щ‘ЩҗЩ„Щ’Щ…ЩҸЩҲЩ…ЩҗЩҶЩҗЩҠЩҶЩҺ",
          "type": "word",
          "verse_key": "48:20",
          "position": 15
        },
        {
          "code": 61806,
          "char": "п…®",
          "font": "QCF4_Warsh_43",
          "text": "ЩҲЩҺЩҠЩҺЩҮЩ’ШҜЩҗЩҠЩҺЩғЩҸЩ…Щ’",
          "type": "word",
          "verse_key": "48:20",
          "position": 16
        },
        {
          "code": 61807,
          "char": "п…Ҝ",
          "font": "QCF4_Warsh_43",
          "text": "ШөЩҗШұЩҺЩ°Ш·Ш§Щ—",
          "type": "word",
          "verse_key": "48:20",
          "position": 17
        }
      ]
    },
    {
      "line": 12,
      "words": [
        {
          "code": 61808,
          "char": "п…°",
          "font": "QCF4_Warsh_43",
          "text": "Щ…Щ‘ЩҸШіЩ’ШӘЩҺЩӮЩҗЩҠЩ…Ш§Щ—Ы–",
          "type": "word_with_mark",
          "verse_key": "48:20",
          "position": 18
        },
        {
          "code": 61810,
          "char": "п…І",
          "font": "QCF4_Warsh_43",
          "text": "20",
          "type": "aya_end",
          "verse_key": "48:20",
          "aya_num": 20
        },
        {
          "code": 61811,
          "char": "п…і",
          "font": "QCF4_Warsh_43",
          "text": "ЩҲЩҺШЈЩҸШ®Щ’ШұЫӘЩүЩ°",
          "type": "word_with_mark",
          "verse_key": "48:21",
          "position": 1
        },
        {
          "code": 61812,
          "char": "п…ҙ",
          "font": "QCF4_Warsh_43",
          "text": "Щ„ЩҺЩ…Щ’",
          "type": "word",
          "verse_key": "48:21",
          "position": 2
        },
        {
          "code": 61813,
          "char": "п…ө",
          "font": "QCF4_Warsh_43",
          "text": "ШӘЩҺЩӮЩ’ШҜЩҗШұЩҸЩҲШ§Щ’",
          "type": "word",
          "verse_key": "48:21",
          "position": 3
        },
        {
          "code": 61814,
          "char": "п…¶",
          "font": "QCF4_Warsh_43",
          "text": "Ш№ЩҺЩ„ЩҺЩҠЩ’ЩҮЩҺШ§",
          "type": "word",
          "verse_key": "48:21",
          "position": 4
        },
        {
          "code": 61815,
          "char": "п…·",
          "font": "QCF4_Warsh_43",
          "text": "ЩӮЩҺШҜЩҺ",
          "type": "word",
          "verse_key": "48:21",
          "position": 5
        },
        {
          "code": 61816,
          "char": "п…ё",
          "font": "QCF4_Warsh_43",
          "text": "Ш§ЩҺШӯЩҺШ§Ш·ЩҺ",
          "type": "word",
          "verse_key": "48:21",
          "position": 6
        },
        {
          "code": 61817,
          "char": "п…№",
          "font": "QCF4_Warsh_43",
          "text": "Ш§ЩҺЫ¬Щ„Щ„Щ‘ЩҺЩҮЩҸ",
          "type": "word_with_mark",
          "verse_key": "48:21",
          "position": 7
        },
        {
          "code": 61818,
          "char": "п…ә",
          "font": "QCF4_Warsh_43",
          "text": "ШЁЩҗЩҮЩҺШ§Ы–",
          "type": "word_with_mark",
          "verse_key": "48:21",
          "position": 8
        }
      ]
    },
    {
      "line": 13,
      "words": [
        {
          "code": 61820,
          "char": "п…ј",
          "font": "QCF4_Warsh_43",
          "text": "ЩҲЩҺЩғЩҺШ§ЩҶЩҺ",
          "type": "word",
          "verse_key": "48:21",
          "position": 9
        },
        {
          "code": 61821,
          "char": "п…Ҫ",
          "font": "QCF4_Warsh_43",
          "text": "Ш§ЩҺЫ¬Щ„Щ„Щ‘ЩҺЩҮЩҸ",
          "type": "word_with_mark",
          "verse_key": "48:21",
          "position": 10
        },
        {
          "code": 61822,
          "char": "п…ҫ",
          "font": "QCF4_Warsh_43",
          "text": "Ш№ЩҺЩ„ЩҺЩүЩ°",
          "type": "word",
          "verse_key": "48:21",
          "position": 11
        },
        {
          "code": 61823,
          "char": "п…ҝ",
          "font": "QCF4_Warsh_43",
          "text": "ЩғЩҸЩ„Щ‘Щҗ",
          "type": "word",
          "verse_key": "48:21",
          "position": 12
        },
        {
          "code": 61824,
          "char": "пҶҖ",
          "font": "QCF4_Warsh_43",
          "text": "ШҙЩҺЫ’Щ’ШЎЩ–",
          "type": "word",
          "verse_key": "48:21",
          "position": 13
        },
        {
          "code": 61825,
          "char": "пҶҒ",
          "font": "QCF4_Warsh_43",
          "text": "ЩӮЩҺШҜЩҗЩҠШұШ§Щ—Ы–",
          "type": "word_with_mark",
          "verse_key": "48:21",
          "position": 14
        },
        {
          "code": 61827,
          "char": "пҶғ",
          "font": "QCF4_Warsh_43",
          "text": "21",
          "type": "aya_end",
          "verse_key": "48:21",
          "aya_num": 21
        },
        {
          "code": 61828,
          "char": "пҶ„",
          "font": "QCF4_Warsh_43",
          "text": "ЩҲЩҺЩ„ЩҺЩҲЩ’",
          "type": "word",
          "verse_key": "48:22",
          "position": 1
        },
        {
          "code": 61829,
          "char": "пҶ…",
          "font": "QCF4_Warsh_43",
          "text": "ЩӮЩҺЩ°ШӘЩҺЩ„ЩҺЩғЩҸЩ…ЩҸ",
          "type": "word",
          "verse_key": "48:22",
          "position": 2
        },
        {
          "code": 61830,
          "char": "пҶҶ",
          "font": "QCF4_Warsh_43",
          "text": "Ш§ЩҸЫ¬Щ„Ш°ЩҗЩҠЩҶЩҺ",
          "type": "word_with_mark",
          "verse_key": "48:22",
          "position": 3
        }
      ]
    },
    {
      "line": 14,
      "words": [
        {
          "code": 61831,
          "char": "пҶҮ",
          "font": "QCF4_Warsh_43",
          "text": "ЩғЩҺЩҒЩҺШұЩҸЩҲШ§Щ’",
          "type": "word",
          "verse_key": "48:22",
          "position": 4
        },
        {
          "code": 61832,
          "char": "пҶҲ",
          "font": "QCF4_Warsh_43",
          "text": "Щ„ЩҺЩҲЩҺЩ„Щ‘ЩҺЩҲЩҸШ§Щ’",
          "type": "word",
          "verse_key": "48:22",
          "position": 5
        },
        {
          "code": 61833,
          "char": "пҶү",
          "font": "QCF4_Warsh_43",
          "text": "Ш§ЩҸЫ¬Щ„ЩҺШ§ШҜЩ’ШЁЩҺЩ°ШұЩҺ",
          "type": "word_with_mark",
          "verse_key": "48:22",
          "position": 6
        },
        {
          "code": 61834,
          "char": "пҶҠ",
          "font": "QCF4_Warsh_43",
          "text": "Ш«ЩҸЩ…Щ‘ЩҺ",
          "type": "word",
          "verse_key": "48:22",
          "position": 7
        },
        {
          "code": 61835,
          "char": "пҶӢ",
          "font": "QCF4_Warsh_43",
          "text": "Щ„ЩҺШ§",
          "type": "word",
          "verse_key": "48:22",
          "position": 8
        },
        {
          "code": 61836,
          "char": "пҶҢ",
          "font": "QCF4_Warsh_43",
          "text": "ЩҠЩҺШ¬ЩҗШҜЩҸЩҲЩҶЩҺ",
          "type": "word",
          "verse_key": "48:22",
          "position": 9
        },
        {
          "code": 61837,
          "char": "пҶҚ",
          "font": "QCF4_Warsh_43",
          "text": "ЩҲЩҺЩ„ЩҗЩҠЩ‘Ш§Щ—",
          "type": "word",
          "verse_key": "48:22",
          "position": 10
        },
        {
          "code": 61838,
          "char": "пҶҺ",
          "font": "QCF4_Warsh_43",
          "text": "ЩҲЩҺЩ„ЩҺШ§",
          "type": "word",
          "verse_key": "48:22",
          "position": 11
        },
        {
          "code": 61839,
          "char": "пҶҸ",
          "font": "QCF4_Warsh_43",
          "text": "ЩҶЩҺШөЩҗЩҠШұШ§Щ—Ы–",
          "type": "word_with_mark",
          "verse_key": "48:22",
          "position": 12
        },
        {
          "code": 61841,
          "char": "пҶ‘",
          "font": "QCF4_Warsh_43",
          "text": "22",
          "type": "aya_end",
          "verse_key": "48:22",
          "aya_num": 22
        },
        {
          "code": 61842,
          "char": "пҶ’",
          "font": "QCF4_Warsh_43",
          "text": "ШіЩҸЩҶЩ‘ЩҺШ©ЩҺ",
          "type": "word",
          "verse_key": "48:23",
          "position": 1
        }
      ]
    },
    {
      "line": 15,
      "words": [
        {
          "code": 61843,
          "char": "пҶ“",
          "font": "QCF4_Warsh_43",
          "text": "Ш§ЩҺЫ¬Щ„Щ„Щ‘ЩҺЩҮЩҗ",
          "type": "word_with_mark",
          "verse_key": "48:23",
          "position": 2
        },
        {
          "code": 61844,
          "char": "пҶ”",
          "font": "QCF4_Warsh_43",
          "text": "Ш§ЩҗЫ¬Щ„ШӘЩҗЫ’",
          "type": "word_with_mark",
          "verse_key": "48:23",
          "position": 3
        },
        {
          "code": 61845,
          "char": "пҶ•",
          "font": "QCF4_Warsh_43",
          "text": "ЩӮЩҺШҜЩ’",
          "type": "word",
          "verse_key": "48:23",
          "position": 4
        },
        {
          "code": 61846,
          "char": "пҶ–",
          "font": "QCF4_Warsh_43",
          "text": "Ш®ЩҺЩ„ЩҺШӘЩ’",
          "type": "word",
          "verse_key": "48:23",
          "position": 5
        },
        {
          "code": 61847,
          "char": "пҶ—",
          "font": "QCF4_Warsh_43",
          "text": "Щ…ЩҗЩҶ",
          "type": "word",
          "verse_key": "48:23",
          "position": 6
        },
        {
          "code": 61848,
          "char": "пҶҳ",
          "font": "QCF4_Warsh_43",
          "text": "ЩӮЩҺШЁЩ’Щ„ЩҸЫ–",
          "type": "word_with_mark",
          "verse_key": "48:23",
          "position": 7
        },
        {
          "code": 61850,
          "char": "пҶҡ",
          "font": "QCF4_Warsh_43",
          "text": "ЩҲЩҺЩ„ЩҺЩҶ",
          "type": "word",
          "verse_key": "48:23",
          "position": 8
        },
        {
          "code": 61851,
          "char": "пҶӣ",
          "font": "QCF4_Warsh_43",
          "text": "ШӘЩҺШ¬ЩҗШҜЩҺ",
          "type": "word",
          "verse_key": "48:23",
          "position": 9
        },
        {
          "code": 61852,
          "char": "пҶң",
          "font": "QCF4_Warsh_43",
          "text": "Щ„ЩҗШіЩҸЩҶЩ‘ЩҺШ©Щҗ",
          "type": "word",
          "verse_key": "48:23",
          "position": 10
        },
        {
          "code": 61853,
          "char": "пҶқ",
          "font": "QCF4_Warsh_43",
          "text": "Ш§ЩҗЫ¬Щ„Щ„Щ‘ЩҺЩҮЩҗ",
          "type": "word_with_mark",
          "verse_key": "48:23",
          "position": 11
        },
        {
          "code": 61854,
          "char": "пҶһ",
          "font": "QCF4_Warsh_43",
          "text": "ШӘЩҺШЁЩ’ШҜЩҗЩҠЩ„Ш§Щ—Ы–",
          "type": "word_with_mark",
          "verse_key": "48:23",
          "position": 12
        },
        {
          "code": 61856,
          "char": "пҶ ",
          "font": "QCF4_Warsh_43",
          "text": "23",
          "type": "aya_end",
          "verse_key": "48:23",
          "aya_num": 23
        }
      ]
    }
  ]
}